keylight/__init__.py
keylight/cli.py
keylight/constants.py
keylight/main.py
keylight/types.py
keylight-0.1.3.dist-info/LICENSE
keylight-0.1.3.dist-info/METADATA
keylight-0.1.3.dist-info/WHEEL
keylight-0.1.3.dist-info/RECORD
