Metadata-Version: 2.1
Name: keylight
Version: 0.1.3
Summary: A CLI to control an Elgato Key Light
Author: andornaut
Author-email: andornaut@users.noreply.github.com
Requires-Python: >=3.12,<3.13
Classifier: Programming Language :: Python :: 3
Classifier: Programming Language :: Python :: 3.12
Requires-Dist: leglight (>=0.2.0,<0.3.0)
Requires-Dist: typer (>=0.9.0,<0.10.0)
